{
  "mainMenu": {},
  "title": "====== Main Menu ======",
  "welcomeMessage": "Welcome to Dr. Rags Sokoban!\n======================",
  "noSaveOptions": [
    "Press 1 to start the game",
    "Press 2 to exit"
  ],
  "saveExistsOptions": [
    "Press 1 to start the game",
    "Press 2 to continue",
    "Press 3 to exit"
  ],
  "footer": "\n===== Controls ===== \n- Arrow Keys for movement \n- ctrl + Z to undo the last move. \n- ctrl + S to save the game. \n- 'P' to pause the game.\n========================"  
}